TauLidarCommon/__init__.py
TauLidarCommon/__version__.py
TauLidarCommon/color.py
TauLidarCommon/d3.py
TauLidarCommon/frame.py
TauLidarCommon-0.0.2.dist-info/LICENSE
TauLidarCommon-0.0.2.dist-info/METADATA
TauLidarCommon-0.0.2.dist-info/WHEEL
TauLidarCommon-0.0.2.dist-info/top_level.txt
TauLidarCommon-0.0.2.dist-info/RECORD
