Metadata-Version: 2.1
Name: TauLidarCommon
Version: 0.0.2
Summary: Tau LiDAR common package
Home-page: https://github.com/OnionIoT/tau-lidar-common
Author: Onion Corporation
Author-email: hello@onioniot.com
License: MIT
Platform: UNKNOWN
Classifier: Programming Language :: Python :: 3
Classifier: License :: OSI Approved :: MIT License
Classifier: Operating System :: OS Independent
Requires-Python: >=3.6.1
